gtin/GCPPrefixFormatList.xml
gtin/__init__.py
gtin/__main__.py
gtin/py.typed
gtin-1.3.1649173518.data/data/gtin/GCPPrefixFormatList.xml
gtin-1.3.1649173518.data/data/gtin/py.typed
gtin-1.3.1649173518.dist-info/LICENSE
gtin-1.3.1649173518.dist-info/METADATA
gtin-1.3.1649173518.dist-info/WHEEL
gtin-1.3.1649173518.dist-info/entry_points.txt
gtin-1.3.1649173518.dist-info/top_level.txt
gtin-1.3.1649173518.dist-info/RECORD
