Metadata-Version: 2.1
Name: gtin
Version: 1.3.1649173518
Summary: Parse GTINs (also known as UPC/EAN/JAN/ISBN)
Home-page: https://github.com/enorganic/gtin
Author-email: david@belais.me
License: MIT
Keywords: gtin,upc,ean,jan,isbn,gs1
Platform: UNKNOWN
Requires-Python: ~=3.6
License-File: LICENSE
